paymentrails/__init__.py
paymentrails/balances.py
paymentrails/balances_gateway.py
paymentrails/batch.py
paymentrails/batch_gateway.py
paymentrails/batch_summary.py
paymentrails/client.py
paymentrails/configuration.py
paymentrails/gateway.py
paymentrails/payment.py
paymentrails/payment_gateway.py
paymentrails/recipient.py
paymentrails/recipient_account.py
paymentrails/recipient_account_gateway.py
paymentrails/recipient_gateway.py
paymentrails/utils.py
paymentrails/exceptions/__init__.py
paymentrails/exceptions/authenticationException.py
paymentrails/exceptions/authorizationException.py
paymentrails/exceptions/downForMaintenanceException.py
paymentrails/exceptions/invalidFieldException.py
paymentrails/exceptions/invalidServerConnectionException.py
paymentrails/exceptions/invalidStatusException.py
paymentrails/exceptions/malformedException.py
paymentrails/exceptions/notFoundException.py
paymentrails/exceptions/tooManyRequestsException.py
paymentrails/exceptions/unexpectedException.py
paymentrails-0.2.dist-info/LICENSE
paymentrails-0.2.dist-info/METADATA
paymentrails-0.2.dist-info/WHEEL
paymentrails-0.2.dist-info/top_level.txt
paymentrails-0.2.dist-info/RECORD
