Metadata-Version: 2.1
Name: paymentrails
Version: 0.2
Home-page: 
Author: Trolley
Author-email: developer-tools@trolley.com
License-File: LICENSE
Requires-Dist: requests (>=2.13.0)
